danski_utils/__init__.py
danski_utils/danski_utils.py
danski_utils-0.1.0.dist-info/AUTHORS.rst
danski_utils-0.1.0.dist-info/LICENSE
danski_utils-0.1.0.dist-info/METADATA
danski_utils-0.1.0.dist-info/WHEEL
danski_utils-0.1.0.dist-info/top_level.txt
danski_utils-0.1.0.dist-info/RECORD
