Metadata-Version: 2.1
Name: danski-utils
Version: 0.1.0
Summary: A collection of utils that I use often
Home-page: https://github.com/gus0k/danski_utils
Author: Diego Kiedanski
Author-email: dkiedanski@gmail.com
License: MIT license
Keywords: danski_utils
Platform: UNKNOWN
Classifier: Development Status :: 2 - Pre-Alpha
Classifier: Intended Audience :: Developers
Classifier: License :: OSI Approved :: MIT License
Classifier: Natural Language :: English
Classifier: Programming Language :: Python :: 3
Classifier: Programming Language :: Python :: 3.5
Classifier: Programming Language :: Python :: 3.6
Classifier: Programming Language :: Python :: 3.7
Classifier: Programming Language :: Python :: 3.8
Requires-Python: >=3.5
